agent.py
api_key_middleware.py
auth_context.py
auth_middleware.py
main.py
session_manager.py
api/__init__.py
api/auth.py
api/chat.py
api/connector_router.py
api/connectors.py
api/docling.py
api/documents.py
api/flows.py
api/keys.py
api/knowledge_filter.py
api/langflow_files.py
api/models.py
api/nudges.py
api/oidc.py
api/provider_health.py
api/provider_validation.py
api/router.py
api/search.py
api/settings.py
api/tasks.py
api/upload.py
api/v1/__init__.py
api/v1/chat.py
api/v1/documents.py
api/v1/knowledge_filters.py
api/v1/search.py
api/v1/settings.py
config/__init__.py
config/config_manager.py
config/settings.py
connectors/__init__.py
connectors/base.py
connectors/connection_manager.py
connectors/langflow_connector_service.py
connectors/service.py
connectors/google_drive/__init__.py
connectors/google_drive/connector.py
connectors/google_drive/oauth.py
connectors/onedrive/__init__.py
connectors/onedrive/connector.py
connectors/onedrive/oauth.py
connectors/sharepoint/__init__.py
connectors/sharepoint/connector.py
connectors/sharepoint/oauth.py
models/__init__.py
models/processors.py
models/tasks.py
openrag-0.2.0.dist-info/licenses/LICENSE
services/__init__.py
services/api_key_service.py
services/auth_service.py
services/chat_service.py
services/conversation_persistence_service.py
services/document_service.py
services/flows_service.py
services/knowledge_filter_service.py
services/langflow_file_service.py
services/langflow_history_service.py
services/langflow_mcp_service.py
services/models_service.py
services/monitor_service.py
services/search_service.py
services/session_ownership_service.py
services/task_service.py
tui/__init__.py
tui/main.py
tui/_assets/docker-compose.gpu.yml
tui/_assets/docker-compose.yml
tui/_assets/flows/ingestion_flow.json
tui/_assets/flows/openrag_agent.json
tui/_assets/flows/openrag_nudges.json
tui/_assets/flows/openrag_url_mcp.json
tui/_assets/flows/components/ollama_embedding.json
tui/_assets/flows/components/ollama_llm.json
tui/_assets/flows/components/ollama_llm_text.json
openrag-0.2.0.dist-info/METADATA
openrag-0.2.0.dist-info/WHEEL
openrag-0.2.0.dist-info/entry_points.txt
openrag-0.2.0.dist-info/top_level.txt
openrag-0.2.0.dist-info/RECORD
