Metadata-Version: 2.4
Name: openrag
Version: 0.2.0
Summary: Add your description here
Requires-Python: >=3.13
License-File: LICENSE
Requires-Dist: agentd>=0.2.2
Requires-Dist: aiofiles>=24.1.0
Requires-Dist: cryptography>=45.0.6
Requires-Dist: docling[vlm]==2.41.0; sys_platform != "darwin"
Requires-Dist: docling[ocrmac,vlm]==2.41.0; sys_platform == "darwin"
Requires-Dist: google-api-python-client>=2.143.0
Requires-Dist: google-auth-httplib2>=0.2.0
Requires-Dist: google-auth-oauthlib>=1.2.0
Requires-Dist: msal>=1.29.0
Requires-Dist: httpx>=0.27.0
Requires-Dist: opensearch-py[async]>=3.0.0
Requires-Dist: pyjwt>=2.8.0
Requires-Dist: python-multipart>=0.0.20
Requires-Dist: starlette>=0.47.1
Requires-Dist: torch>=2.7.1
Requires-Dist: uvicorn>=0.35.0
Requires-Dist: boto3>=1.35.0
Requires-Dist: psutil>=7.0.0
Requires-Dist: rich>=13.0.0
Requires-Dist: textual>=0.45.0
Requires-Dist: python-dotenv>=1.0.0
Requires-Dist: textual-fspicker>=0.6.0
Requires-Dist: structlog>=25.4.0
Requires-Dist: docling-serve==1.5.0
Requires-Dist: docling-core==2.48.1
Requires-Dist: easyocr>=1.7.1; sys_platform != "darwin"
Requires-Dist: zxcvbn>=4.5.0
Dynamic: license-file
